idonethis.py
idonethis-1.0.0.dist-info/top_level.txt
idonethis-1.0.0.dist-info/entry_points.txt
idonethis-1.0.0.dist-info/METADATA
idonethis-1.0.0.dist-info/DESCRIPTION.rst
idonethis-1.0.0.dist-info/metadata.json
idonethis-1.0.0.dist-info/WHEEL
idonethis-1.0.0.dist-info/RECORD
